socketnest/__init__.py
socketnest/example.py
socketnest/socketnest.py
socketnest-0.1.0.dist-info/licenses/LICENSE
socketnest_python/__init__.py
socketnest_python/example.py
socketnest_python/socketnest.py
socketnest-0.1.0.dist-info/METADATA
socketnest-0.1.0.dist-info/WHEEL
socketnest-0.1.0.dist-info/top_level.txt
socketnest-0.1.0.dist-info/RECORD
